whoisrws/__init__.py
whoisrws-0.1.0.dist-info/METADATA
whoisrws-0.1.0.dist-info/WHEEL
whoisrws-0.1.0.dist-info/top_level.txt
whoisrws-0.1.0.dist-info/RECORD
