Metadata-Version: 2.1
Name: whoisrws
Version: 0.1.0
Summary: A Python Client for the ARIN WHOIS Webservice.
Home-page: https://github.com/Neko-Design/whoisrws
Author: Ewen McCahon
Author-email: hi@ewenmccahon.me
License: apache2
Platform: UNKNOWN
Classifier: Intended Audience :: Developers
Classifier: Intended Audience :: System Administrators
Classifier: Operating System :: OS Independent
Classifier: Topic :: Software Development
Requires-Dist: requests
Requires-Dist: murl
Requires-Dist: IPy
